rush/.ruff_cache/.gitignore
rush/.ruff_cache/0.14.3/4654366173419807847
rush/.ruff_cache/0.14.3/7383249696747722066
rush/.ruff_cache/CACHEDIR.TAG
rush/__init__.py
rush/auto3d.py
rush/boltz.py
rush/client.py
rush/convert/__init__.py
rush/convert/json.py
rush/convert/mmcif.py
rush/convert/pdb.py
rush/convert/sdf.py
rush/exess.py
rush/mmseqs2.py
rush/mol.py
rush/nnxtb.py
rush/pbsa.py
rush/prepare_complex.py
rush/prepare_protein.py
rush/trc/merge.py
rush/utils.py
rush_py-6.0.2.dist-info/WHEEL
rush_py-6.0.2.dist-info/METADATA
rush_py-6.0.2.dist-info/RECORD
