Metadata-Version: 2.3
Name: rush-py
Version: 6.0.2
Summary: Python client for QDX's Rush platform
Keywords: computational-chemistry,quantum-chemistry,HPC,molecular-modeling,protein-folding,EXESS,NN-xTB,PBSA
Author: Sean Laguna
Author-email: Sean Laguna <seanlaguna@qdx.co>
License: Apache-2.0
Classifier: License :: OSI Approved :: Apache Software License
Classifier: Programming Language :: Python :: 3
Classifier: Programming Language :: Python :: 3.12
Classifier: Intended Audience :: Healthcare Industry
Classifier: Intended Audience :: Science/Research
Classifier: Topic :: Scientific/Engineering :: Bio-Informatics
Classifier: Topic :: Scientific/Engineering :: Chemistry
Classifier: Topic :: System :: Distributed Computing
Requires-Dist: gql~=4.0
Requires-Dist: h5py~=3.14
Requires-Dist: rdkit~=2025.9.2
Requires-Dist: requests~=2.32
Requires-Dist: requests-toolbelt~=1.0
Requires-Dist: zstandard~=0.23
Requires-Python: >=3.12
Project-URL: Documentation, https://talo.github.io/rush-py
Project-URL: Homepage, https://rush.cloud
Project-URL: Issues, https://github.com/talo/rush-py/issues
Project-URL: Source, https://github.com/talo/rush-py
